.hgignore
LICENSE
MANIFEST.in
README.rst
setup.py
json_resource_http/__init__.py
json_resource_http/exceptions.py
json_resource_http/queryset.py
json_resource_http/resource.py
json_resource_http/schema.py
json_resource_http.egg-info/PKG-INFO
json_resource_http.egg-info/SOURCES.txt
json_resource_http.egg-info/dependency_links.txt
json_resource_http.egg-info/requires.txt
json_resource_http.egg-info/top_level.txt
json_resource_http/test/__init__.py
json_resource_http/test/conftest.py
json_resource_http/test/test_resource.py
json_resource_http/test/testcase.py
json_resource_http/test/schemas/test-collection.json
json_resource_http/test/schemas/test.json