Metadata-Version: 1.0
Name: json-resource-http
Version: 0.1.5
Summary: UNKNOWN
Home-page: UNKNOWN
Author: Ernst Odolphi
Author-email: ernst.odolphi@gmail.com
License: UNKNOWN
Platform: UNKNOWN
